qcrypto/__init__.py
qcrypto/bb84.py
qcrypto/classical_crypto.py
qcrypto/e91.py
qcrypto/eavesdropping.py
qcrypto/noise.py
qcrypto/quantum_gates.py
qcrypto/quantum_states.py
qcrypto/qubits.py
qcrypto/utils.py
qcrypto_a7-1.0.0.dist-info/METADATA
qcrypto_a7-1.0.0.dist-info/WHEEL
qcrypto_a7-1.0.0.dist-info/top_level.txt
qcrypto_a7-1.0.0.dist-info/RECORD
