Metadata-Version: 2.4
Name: qcrypto-a7
Version: 1.0.0
Summary: Quantum Cryptography Simulation Package (BB84 & E91)
Author: Patnam Kannabhiram
License: MIT
Requires-Python: >=3.8
